{"money":1000,"player":{"data":{"instanceID":48278},"currentExp":0,"currentHp":166},"itemList":[{"number":1,"count":5}],"armorList":[{"data":{"instanceID":47626},"number":2,"lev":1,"currentExp":0,"isEquip":false},{"data":{"instanceID":47242},"number":3,"lev":1,"currentExp":0,"isEquip":false},{"data":{"instanceID":48446},"number":4,"lev":1,"currentExp":0,"isEquip":false},{"data":{"instanceID":48072},"number":5,"lev":1,"currentExp":0,"isEquip":false},{"data":{"instanceID":48052},"number":10,"lev":1,"currentExp":0,"isEquip":true},{"data":{"instanceID":47618},"number":11,"lev":1,"currentExp":0,"isEquip":true},{"data":{"instanceID":47658},"number":12,"lev":1,"currentExp":0,"isEquip":true},{"data":{"instanceID":47896},"number":13,"lev":1,"currentExp":0,"isEquip":true},{"data":{"instanceID":47626},"number":2,"lev":1,"currentExp":0,"isEquip":false},{"data":{"instanceID":47686},"number":8,"lev":1,"currentExp":0,"isEquip":false},{"data":{"instanceID":48136},"number":9,"lev":1,"currentExp":0,"isEquip":false},{"data":{"instanceID":47684},"number":14,"lev":1,"currentExp":0,"isEquip":false},{"data":{"instanceID":47844},"number":15,"lev":1,"currentExp":0,"isEquip":false},{"data":{"instanceID":47758},"number":16,"lev":1,"currentExp":0,"isEquip":false},{"data":{"instanceID":47626},"number":2,"lev":1,"currentExp":0,"isEquip":false},{"data":{"instanceID":47242},"number":3,"lev":1,"currentExp":0,"isEquip":false},{"data":{"instanceID":48446},"number":4,"lev":1,"currentExp":0,"isEquip":false},{"data":{"instanceID":48072},"number":5,"lev":1,"currentExp":0,"isEquip":false},{"data":{"instanceID":48052},"number":10,"lev":1,"currentExp":0,"isEquip":false},{"data":{"instanceID":47618},"number":11,"lev":1,"currentExp":0,"isEquip":false},{"data":{"instanceID":47658},"number":12,"lev":1,"currentExp":0,"isEquip":false},{"data":{"instanceID":47896},"number":13,"lev":1,"currentExp":0,"isEquip":false},{"data":{"instanceID":47626},"number":2,"lev":1,"currentExp":0,"isEquip":false},{"data":{"instanceID":47686},"number":8,"lev":1,"currentExp":0,"isEquip":false},{"data":{"instanceID":48136},"number":9,"lev":1,"currentExp":0,"isEquip":false},{"data":{"instanceID":47626},"number":2,"lev":1,"currentExp":0,"isEquip":false},{"data":{"instanceID":47242},"number":3,"lev":1,"currentExp":0,"isEquip":false},{"data":{"instanceID":48446},"number":4,"lev":1,"currentExp":0,"isEquip":false},{"data":{"instanceID":48072},"number":5,"lev":1,"currentExp":0,"isEquip":false},{"data":{"instanceID":47626},"number":2,"lev":1,"currentExp":0,"isEquip":false},{"data":{"instanceID":47242},"number":3,"lev":1,"currentExp":0,"isEquip":false},{"data":{"instanceID":48446},"number":4,"lev":1,"currentExp":0,"isEquip":false},{"data":{"instanceID":48072},"number":5,"lev":1,"currentExp":0,"isEquip":false},{"data":{"instanceID":47626},"number":2,"lev":1,"currentExp":0,"isEquip":false},{"data":{"instanceID":47242},"number":3,"lev":1,"currentExp":0,"isEquip":false},{"data":{"instanceID":48446},"number":4,"lev":1,"currentExp":0,"isEquip":false},{"data":{"instanceID":48072},"number":5,"lev":1,"currentExp":0,"isEquip":false}],"weaponList":[{"data":{"instanceID":48108},"number":1,"lev":1,"currentExp":0,"equipNumber":1},{"data":{"instanceID":47114},"number":2,"lev":1,"currentExp":0,"equipNumber":0},{"data":{"instanceID":48078},"number":4,"lev":1,"currentExp":0,"equipNumber":0},{"data":{"instanceID":48428},"number":3,"lev":1,"currentExp":0,"equipNumber":0},{"data":{"instanceID":48416},"number":5,"lev":1,"currentExp":0,"equipNumber":0},{"data":{"instanceID":47114},"number":2,"lev":1,"currentExp":0,"equipNumber":0},{"data":{"instanceID":48078},"number":4,"lev":1,"currentExp":0,"equipNumber":0},{"data":{"instanceID":48428},"number":3,"lev":1,"currentExp":0,"equipNumber":0},{"data":{"instanceID":47114},"number":2,"lev":1,"currentExp":0,"equipNumber":0},{"data":{"instanceID":47114},"number":2,"lev":1,"currentExp":0,"equipNumber":0},{"data":{"instanceID":47114},"number":2,"lev":1,"currentExp":0,"equipNumber":0}],"isFindEnemyList":[false,true,true,true,true],"isFindNpcList":[true],"eventNumber":0,"volumeList":[80,80],"onChageWeapon":{"m_PersistentCalls":{"m_Calls":[]}}}
